videoprops/__init__.py
videoprops/__main__.py
videoprops/binary_dependencies/ffprobe
videoprops/binary_dependencies/ffprobe.exe
get_video_properties-0.1.0.dist-info/LICENSE
get_video_properties-0.1.0.dist-info/METADATA
get_video_properties-0.1.0.dist-info/WHEEL
get_video_properties-0.1.0.dist-info/entry_points.txt
get_video_properties-0.1.0.dist-info/top_level.txt
get_video_properties-0.1.0.dist-info/RECORD
