Metadata-Version: 2.1
Name: get-video-properties
Version: 0.1.0
Summary: Get video properties
Home-page: https://github.com/mvasilkov/python-get-video-properties
Author: Mark Vasilkov
Author-email: mvasilkov@gmail.com
License: MIT
Keywords: ffprobe video audio
Platform: UNKNOWN
Classifier: Intended Audience :: Developers
Classifier: Intended Audience :: End Users/Desktop
Classifier: License :: OSI Approved :: MIT License
Classifier: Programming Language :: Python :: 3
Classifier: Programming Language :: Python :: 3 :: Only
Classifier: Topic :: Multimedia :: Sound/Audio
Classifier: Topic :: Multimedia :: Video
